corby/__init__.py
corby/__main__.py
corby/index.py
corby/generator/__init__.py
corby/generator/base.py
corby/generator/chatbot/__init__.py
corby/generator/chatbot/base_chatbot.py
corby/generator/chatbot/cli.py
corby/generator/chatbot/index.py
corby/generator/chatbot/telegram.py
corby/generator/chatbot/web.py
corby/generator/notebook/__init__.py
corby/generator/notebook/index.py
corby-0.1.4.dist-info/LICENSE
corby-0.1.4.dist-info/METADATA
corby-0.1.4.dist-info/WHEEL
corby-0.1.4.dist-info/entry_points.txt
corby-0.1.4.dist-info/top_level.txt
corby-0.1.4.dist-info/RECORD
