Metadata-Version: 2.1
Name: corby
Version: 0.1.4
Summary: ⚡ Create your LLMs applications from zero to deploy in minutes ⚡
Author: Jose Hervás Díaz
Author-email: jhervasdiaz@gmail.com
License: MIT
License-File: LICENSE
Requires-Dist: inquirer
Requires-Dist: jinja2
Requires-Dist: gitpython
